<?xml version="1.0" encoding="ASCII"?>
<scene>
	<camera>
		<position>0, 0, 0</position>
		<direction>0, 0, 1</direction>
		<rotation>0, 0, 0</rotation>
		<glare>off</glare>
	    <fov>90.0</fov>
	</camera>
	<window>
		<title>bump_cylinder</title>
		<dimension>800, 600</dimension>
		<ambient>0.0</ambient>
	</window>
	<light>
		<position>10, 10, -15</position>
		<intensity>700</intensity>
		<color>0xffffff</color>
		<type>point</type>
	</light>
	<object>
		<type>cylinder</type>
		<position>0, 0, 20</position>
		<direction>0, 1, 0</direction>
		<dimension>10</dimension>
		<rotation>0, 45, 0</rotation>
		<color>0xffffff</color>
		<shine>100, 1</shine>
		<bump_map>bump_textures/liquid.xpm, 10000</bump_map>
	</object>
</scene>
